swutils.py
swutils-0.11.1.dist-info/DESCRIPTION.rst
swutils-0.11.1.dist-info/METADATA
swutils-0.11.1.dist-info/metadata.json
swutils-0.11.1.dist-info/RECORD
swutils-0.11.1.dist-info/top_level.txt
swutils-0.11.1.dist-info/WHEEL
