Metadata-Version: 2.0
Name: swutils
Version: 0.11.1
Summary: ScraperWiki box utility library
Home-page: https://github.com/reubano/swutils
Author: Reuben Cummings
Author-email: reubano@gmail.com
License: MIT
Keywords: swutils
Platform: MacOS X
Platform: Windows
Platform: Linux
Classifier: License :: OSI Approved :: MIT License
Classifier: Development Status :: 4 - Beta
Classifier: Natural Language :: English
Classifier: Programming Language :: Python :: 2
Classifier: Programming Language :: Python :: 2.7
Classifier: Environment :: Console
Classifier: Intended Audience :: Developers
Classifier: Intended Audience :: End Users/Desktop
Classifier: Operating System :: MacOS :: MacOS X
Classifier: Operating System :: POSIX
Classifier: Operating System :: POSIX :: Linux
Requires-Dist: scraperwiki (==0.4.1)
Requires-Dist: pkutils (==0.6.1)
Requires-Dist: schedule (==0.3.2)
Requires-Dist: SQLAlchemy (==1.0.6)
Requires-Dist: tabutils (==0.23.1)
